ecliptor/__init__.py
ecliptor/ecliptor.py
ecliptor/exceptions.py
ecliptor-0.1.3.dist-info/LICENSE
ecliptor-0.1.3.dist-info/METADATA
ecliptor-0.1.3.dist-info/WHEEL
ecliptor-0.1.3.dist-info/top_level.txt
ecliptor-0.1.3.dist-info/RECORD
