Metadata-Version: 2.1
Name: ecliptor
Version: 0.1.3
Summary: Python SDK for the Ecliptor API
Home-page: https://github.com/Ecliptor/ecliptor-python-sdk
Author: Nanki Grewal
Author-email: nanki@ecliptor.ai
Classifier: Development Status :: 3 - Alpha
Classifier: Intended Audience :: Developers
Classifier: License :: OSI Approved :: MIT License
Classifier: Operating System :: OS Independent
Classifier: Programming Language :: Python :: 3
Classifier: Programming Language :: Python :: 3.7
Classifier: Programming Language :: Python :: 3.8
Classifier: Programming Language :: Python :: 3.9
Classifier: Programming Language :: Python :: 3.10
Requires-Python: >=3.7
License-File: LICENSE
Requires-Dist: requests >=2.25.0
Provides-Extra: dev
Requires-Dist: pytest >=6.0 ; extra == 'dev'
Requires-Dist: flake8 >=3.9.0 ; extra == 'dev'
